.gitignore
MANIFEST.in
setup.py
ebs/__init__.py
ebs/linuxnode/__init__.py
ebs/linuxnode/gui/__init__.py
ebs/linuxnode/gui/kivy/__init__.py
ebs/linuxnode/gui/kivy/modapi/__init__.py
ebs/linuxnode/gui/kivy/modapi/mixin.py
ebs/linuxnode/gui/kivy/modapi/images/no-internet.png
ebs/linuxnode/gui/kivy/modapi/images/no-server.png
ebs/linuxnode/modapi/__init__.py
ebs/linuxnode/modapi/manager.py
ebs/linuxnode/modapi/primitives.py
ebs/linuxnode/modapi/standalone.py
ebs/linuxnode/modapi/engines/__init__.py
ebs/linuxnode/modapi/engines/base.py
ebs/linuxnode/modapi/engines/exceptions.py
ebs/linuxnode/modapi/engines/http.py
ebs/linuxnode/modapi/engines/amqp/__init__.py
ebs/linuxnode/modapi/engines/amqp/commands.py
ebs/linuxnode/modapi/engines/amqp/core.py
ebs/linuxnode/modapi/engines/mq/__init__.py
ebs/linuxnode/modapi/engines/mq/commands.py
ebs/linuxnode/modapi/engines/mqtt/__init__.py
ebs/linuxnode/modapi/engines/mqtt/commands.py
ebs/linuxnode/modapi/engines/mqtt/core.py
ebs/linuxnode/mq/__init__.py
ebs/linuxnode/mq/amqp.py
ebs/linuxnode/mq/common.py
ebs/linuxnode/mq/mqtt.py
ebs_linuxnode_modapi.egg-info/PKG-INFO
ebs_linuxnode_modapi.egg-info/SOURCES.txt
ebs_linuxnode_modapi.egg-info/dependency_links.txt
ebs_linuxnode_modapi.egg-info/requires.txt
ebs_linuxnode_modapi.egg-info/top_level.txt